{"timestamp":1739413354,"command_name":"Minitest, Minitest-0, Minitest-1, Minitest-10, Minitest-11, Minitest-12, Minitest-13, Minitest-14, Minitest-15, Minitest-2, Minitest-3, Minitest-4, Minitest-5, Minitest-6, Minitest-7, Minitest-8, Minitest-9","files":[{"filename":"/home/user/git/libregig/app/controllers/admin/admin_controller.rb","covered_percent":100.0,"coverage":{"lines":[13,13,13,null,13,null,13,36,4,null,null,null,null,13,32,null,null,null],"branches":{"[:unless, 0, 8, 6, 11, 9]":{"[:else, 1, 8, 6, 11, 9]":32,"[:then, 2, 9, 8, 10, 28]":4}}},"covered_strength":16.666666666666668,"covered_lines":9,"lines_of_code":9},{"filename":"/home/user/git/libregig/app/controllers/admin/bands_controller.rb","covered_percent":0.0,"coverage":{"lines":[0,0,0,0,0,null,0,0,0,null,0,0,null,0,0,null,0,0,0,0,0,0,0,0,0,null,0,0,0,0,null,0,null,0,0,0,0,null,0,0,0,0,0,0,0],"branches":{}},"covered_strength":0.0,"covered_lines":0,"lines_of_code":37},{"filename":"/home/user/git/libregig/app/controllers/admin/impersonation_controller.rb","covered_percent":100.0,"coverage":{"lines":[6,6,6,6,6,null,null,null,null,null,6,null,null,6,4,null,2,2,2,null,2,2,null,2,null,null,null],"branches":{"[:unless, 0, 15, 6, 15, 115]":{"[:else, 1, 15, 6, 15, 115]":2,"[:then, 2, 15, 6, 15, 84]":2}}},"covered_strength":4.142857142857143,"covered_lines":14,"lines_of_code":14},{"filename":"/home/user/git/libregig/app/controllers/admin/users_controller.rb","covered_percent":100.0,"coverage":{"lines":[11,11,11,null,null,null,11,8,null,8,2,2,null,null,8,null,null,8,4,null,4,null,null,null,11,null,null,11,null,null,11,6,4,2,null,2,2,null,null,null,11,2,2,null,null,11,null,11,14,14,null,null,11,6,null,null,null,null,null,null,null,null],"branches":{"[:\"\u0026.\", 0, 8, 19, 8, 45]":{"[:then, 1, 8, 19, 8, 45]":4,"[:else, 2, 8, 19, 8, 45]":4},"[:if, 3, 10, 6, 13, 9]":{"[:then, 4, 11, 8, 12, 36]":2,"[:else, 5, 10, 6, 13, 9]":6},"[:if, 6, 18, 8, 22, 11]":{"[:then, 7, 19, 10, 19, 43]":4,"[:else, 8, 21, 10, 21, 18]":4},"[:if, 9, 33, 6, 38, 9]":{"[:then, 10, 34, 8, 34, 71]":2,"[:else, 11, 36, 8, 37, 51]":2},"[:unless, 12, 50, 6, 50, 72]":{"[:else, 13, 50, 6, 50, 72]":14,"[:then, 14, 50, 6, 50, 59]":0}}},"covered_strength":7.551724137931035,"covered_lines":29,"lines_of_code":29},{"filename":"/home/user/git/libregig/app/controllers/application_controller.rb","covered_percent":85.33333333333333,"coverage":{"lines":[null,null,17,17,17,17,null,17,722,708,null,null,17,368,112,null,null,17,368,null,null,17,1076,null,null,17,null,17,764,null,null,17,766,4,762,490,null,272,null,null,null,17,4,null,4,null,null,null,4,null,null,null,4,null,null,4,4,null,4,4,null,0,null,null,null,17,null,4,null,null,null,16,null,4,0,0,null,0,null,4,null,null,null,17,4,4,null,null,17,490,490,490,490,null,0,null,null,null,17,272,272,null,null,17,0,0,null,null,17,764,null,2,0,null,2,null,null,null,17,null,272,null,null,null,null,null,null,null,null,null,17,0,0,0,null,null,null,17,2,2,null,null,17,null,354,null,null,null,354,242,null,null,354,null,null],"branches":{"[:unless, 0, 9, 4, 9, 27]":{"[:else, 1, 9, 4, 9, 27]":708,"[:then, 2, 9, 4, 9, 10]":14},"[:\"\u0026.\", 3, 14, 18, 14, 39]":{"[:then, 4, 14, 18, 14, 39]":354,"[:else, 5, 14, 18, 14, 39]":14},"[:unless, 6, 14, 4, 14, 39]":{"[:else, 7, 14, 4, 14, 39]":112,"[:then, 8, 14, 4, 14, 10]":256},"[:if, 9, 19, 4, 19, 43]":{"[:then, 10, 19, 20, 19, 38]":14,"[:else, 11, 19, 41, 19, 43]":354},"[:if, 12, 33, 4, 39, 7]":{"[:then, 13, 34, 6, 34, 35]":4,"[:else, 14, 35, 4, 38, 24]":762},"[:if, 15, 35, 4, 38, 24]":{"[:then, 16, 36, 6, 36, 41]":490,"[:else, 17, 38, 6, 38, 24]":272},"[:if, 18, 59, 4, 63, 7]":{"[:then, 19, 60, 6, 60, 55]":4,"[:else, 20, 62, 6, 62, 32]":0},"[:\"\u0026.\", 21, 68, 27, 68, 48]":{"[:then, 22, 68, 27, 68, 48]":4,"[:else, 23, 68, 27, 68, 48]":0},"[:if, 24, 74, 4, 81, 7]":{"[:then, 25, 75, 6, 78, 11]":0,"[:else, 26, 80, 6, 80, 10]":4},"[:if, 27, 75, 6, 77, 9]":{"[:then, 28, 76, 8, 76, 77]":0,"[:else, 29, 75, 6, 77, 9]":0},"[:if, 30, 91, 4, 96, 7]":{"[:then, 31, 92, 6, 93, 32]":490,"[:else, 32, 95, 6, 95, 24]":0},"[:\"\u0026.\", 33, 110, 14, 110, 38]":{"[:then, 34, 110, 14, 110, 38]":492,"[:else, 35, 110, 14, 110, 38]":272},"[:if, 36, 110, 4, 110, 55]":{"[:then, 37, 110, 4, 110, 10]":762,"[:else, 38, 110, 4, 110, 55]":2},"[:if, 39, 112, 4, 116, 7]":{"[:then, 40, 113, 6, 113, 29]":0,"[:else, 41, 115, 6, 115, 23]":2},"[:unless, 42, 132, 4, 135, 7]":{"[:else, 43, 132, 4, 135, 7]":0,"[:then, 44, 133, 6, 134, 36]":0},"[:if, 45, 149, 4, 151, 7]":{"[:then, 46, 150, 6, 150, 62]":242,"[:else, 47, 149, 4, 151, 7]":112}}},"covered_strength":156.08,"covered_lines":64,"lines_of_code":75},{"filename":"/home/user/git/libregig/app/controllers/bands_controller.rb","covered_percent":95.5223880597015,"coverage":{"lines":[16,16,null,16,16,16,null,16,16,16,16,null,16,null,16,null,null,16,null,16,null,16,2,14,2,null,null,null,16,null,null,16,null,null,16,0,null,null,16,2,null,null,16,4,null,null,4,4,4,null,null,null,null,null,null,null,2,null,2,null,null,null,16,4,2,null,2,null,null,null,16,4,2,null,2,null,null,null,16,null,16,40,null,null,16,0,0,null,null,16,10,null,null,16,16,null,null,16,12,12,12,null,null,16,8,8,null,8,null,null,null,null,16,8,null,null,16,4,null,null,16,16,16,6,null,10,null,null,null,16,8,null,null],"branches":{"[:if, 0, 15, 6, 17, 26]":{"[:then, 1, 16, 8, 16, 16]":0,"[:else, 2, 17, 8, 17, 26]":16},"[:if, 3, 22, 4, 26, 7]":{"[:then, 4, 23, 6, 23, 30]":2,"[:else, 5, 24, 4, 25, 30]":14},"[:if, 6, 24, 4, 25, 30]":{"[:then, 7, 25, 6, 25, 30]":2,"[:else, 8, 24, 4, 25, 30]":12},"[:if, 9, 64, 4, 68, 7]":{"[:then, 10, 65, 6, 65, 65]":2,"[:else, 11, 67, 6, 67, 18]":2},"[:if, 12, 72, 4, 76, 7]":{"[:then, 13, 73, 6, 73, 52]":2,"[:else, 14, 75, 6, 75, 70]":2},"[:if, 15, 82, 13, 82, 64]":{"[:then, 16, 82, 35, 82, 43]":0,"[:else, 17, 82, 46, 82, 64]":40},"[:unless, 18, 87, 4, 87, 38]":{"[:else, 19, 87, 4, 87, 38]":0,"[:then, 20, 87, 4, 87, 25]":0},"[:unless, 21, 91, 4, 91, 60]":{"[:else, 22, 91, 4, 91, 60]":10,"[:then, 23, 91, 4, 91, 21]":0},"[:if, 24, 108, 6, 110, 18]":{"[:then, 25, 109, 8, 109, 22]":0,"[:else, 26, 110, 8, 110, 18]":8},"[:unless, 27, 114, 4, 114, 56]":{"[:else, 28, 114, 4, 114, 56]":6,"[:then, 29, 114, 4, 114, 25]":2},"[:unless, 30, 118, 4, 118, 79]":{"[:else, 31, 118, 4, 118, 79]":4,"[:then, 32, 118, 4, 118, 25]":0},"[:\"\u0026.\", 33, 122, 26, 122, 43]":{"[:then, 34, 122, 26, 122, 43]":8,"[:else, 35, 122, 26, 122, 43]":8},"[:if, 36, 123, 4, 127, 7]":{"[:then, 37, 124, 6, 124, 69]":6,"[:else, 38, 126, 6, 126, 29]":10},"[:if, 39, 124, 30, 124, 67]":{"[:then, 40, 124, 55, 124, 60]":4,"[:else, 41, 124, 63, 124, 67]":2}}},"covered_strength":11.373134328358208,"covered_lines":64,"lines_of_code":67},{"filename":"/home/user/git/libregig/app/controllers/events_controller.rb","covered_percent":98.0,"coverage":{"lines":[17,17,null,17,17,17,null,17,null,17,268,268,268,268,null,null,17,2,2,null,null,17,null,null,17,null,null,17,8,null,6,6,6,null,0,null,null,null,17,20,14,null,4,null,null,null,17,4,2,null,2,null,null,17,null,17,308,null,null,17,30,26,null,null,17,24,null,null,17,30,null,null,17,28,null,null,null,null,null,null,null,28,null,28,28,28,28,2,null,null,null,null,17,6,null,null,null,null,null,null],"branches":{"[:if, 0, 19, 4, 19, 69]":{"[:then, 1, 19, 4, 19, 40]":0,"[:else, 2, 19, 4, 19, 69]":2},"[:if, 3, 31, 4, 36, 7]":{"[:then, 4, 32, 6, 33, 66]":6,"[:else, 5, 35, 6, 35, 48]":0},"[:if, 6, 40, 4, 44, 7]":{"[:then, 7, 41, 6, 41, 67]":14,"[:else, 8, 43, 6, 43, 49]":4},"[:if, 9, 57, 14, 57, 67]":{"[:then, 10, 57, 36, 57, 45]":38,"[:else, 11, 57, 48, 57, 67]":270},"[:unless, 12, 62, 4, 62, 40]":{"[:else, 13, 62, 4, 62, 40]":26,"[:then, 14, 62, 4, 62, 26]":0},"[:unless, 15, 66, 4, 66, 62]":{"[:else, 16, 66, 4, 66, 62]":24,"[:then, 17, 66, 4, 66, 22]":0},"[:if, 18, 87, 6, 89, 9]":{"[:then, 19, 88, 8, 88, 65]":2,"[:else, 20, 87, 6, 89, 9]":26}}},"covered_strength":41.64,"covered_lines":49,"lines_of_code":50},{"filename":"/home/user/git/libregig/app/controllers/members_controller.rb","covered_percent":91.66666666666667,"coverage":{"lines":[9,9,9,null,null,9,null,null,9,null,null,9,null,null,9,2,null,null,9,4,4,null,2,null,null,null,null,null,null,2,null,2,null,null,9,4,4,4,2,null,2,2,null,null,null,0,0,null,null,9,2,2,null,null,9,null,9,18,null,null,9,10,10,null,null,9,0,null,null,9,8,null,null,null,null],"branches":{"[:unless, 0, 21, 4, 21, 73]":{"[:else, 1, 21, 4, 21, 73]":2,"[:then, 2, 21, 4, 21, 53]":2},"[:unless, 3, 30, 4, 30, 77]":{"[:else, 4, 30, 4, 30, 77]":2,"[:then, 5, 30, 4, 30, 53]":0},"[:if, 6, 38, 6, 43, 9]":{"[:then, 7, 39, 8, 39, 82]":2,"[:else, 8, 41, 8, 42, 62]":2},"[:if, 9, 58, 15, 58, 70]":{"[:then, 10, 58, 37, 58, 47]":0,"[:else, 11, 58, 50, 58, 70]":18},"[:unless, 12, 63, 4, 63, 42]":{"[:else, 13, 63, 4, 63, 42]":10,"[:then, 14, 63, 4, 63, 27]":0},"[:unless, 15, 67, 4, 67, 64]":{"[:else, 16, 67, 4, 67, 64]":0,"[:then, 17, 67, 4, 67, 23]":0}}},"covered_strength":6.083333333333333,"covered_lines":33,"lines_of_code":36},{"filename":"/home/user/git/libregig/app/controllers/permissions_controller.rb","covered_percent":98.07692307692308,"coverage":{"lines":[15,15,null,15,15,15,null,15,null,12,2,null,10,null,null,null,null,null,null,15,2,null,null,15,6,6,null,6,6,6,6,6,null,6,2,null,0,null,null,null,15,14,14,6,8,2,null,6,4,2,null,2,null,null,null,2,null,null,15,6,2,2,null,4,null,null,null,15,null,15,12,4,null,null,null,15,8,8,8,null,null,15,20,null,null,15,6,null,null,15,14,null,null],"branches":{"[:if, 0, 10, 6, 17, 9]":{"[:then, 1, 11, 8, 11, 22]":2,"[:else, 2, 13, 8, 16, 9]":10},"[:\"\u0026.\", 3, 32, 4, 32, 38]":{"[:then, 4, 32, 4, 32, 38]":4,"[:else, 5, 32, 4, 32, 38]":2},"[:if, 6, 34, 4, 38, 7]":{"[:then, 7, 35, 6, 35, 64]":2,"[:else, 8, 37, 6, 37, 48]":0},"[:if, 9, 43, 4, 54, 7]":{"[:then, 10, 44, 6, 44, 57]":6,"[:else, 11, 45, 4, 53, 9]":8},"[:if, 12, 45, 4, 53, 9]":{"[:then, 13, 46, 6, 46, 62]":2,"[:else, 14, 48, 6, 53, 9]":6},"[:if, 15, 49, 6, 53, 9]":{"[:then, 16, 50, 8, 50, 67]":2,"[:else, 17, 52, 8, 52, 66]":2},"[:if, 18, 60, 4, 65, 7]":{"[:then, 19, 61, 6, 62, 57]":2,"[:else, 20, 64, 6, 64, 81]":4},"[:unless, 21, 71, 4, 73, 7]":{"[:else, 22, 71, 4, 73, 7]":8,"[:then, 23, 72, 6, 72, 57]":4}}},"covered_strength":9.038461538461538,"covered_lines":51,"lines_of_code":52},{"filename":"/home/user/git/libregig/app/controllers/sessions_controller.rb","covered_percent":100.0,"coverage":{"lines":[17,17,8,8,null,null,17,244,242,242,242,240,240,240,null,2,2,2,2,2,null,null,null,17,2,2,2,null,null,17,null,17,244,null,null],"branches":{"[:if, 0, 3, 4, 3, 43]":{"[:then, 1, 3, 4, 3, 27]":4,"[:else, 2, 3, 4, 3, 43]":4},"[:if, 3, 11, 4, 21, 7]":{"[:then, 4, 12, 6, 14, 64]":240,"[:else, 5, 16, 6, 20, 48]":2}}},"covered_strength":86.16666666666667,"covered_lines":24,"lines_of_code":24},{"filename":"/home/user/git/libregig/app/controllers/user_mails_controller.rb","covered_percent":100.0,"coverage":{"lines":[10,10,10,null,10,null,null,10,null,6,2,null,4,null,null,null,10,4,null,4,2,null,2,null,null,null,10,null,10,10,null,null,10,10,null,4,null,null],"branches":{"[:if, 0, 10, 6, 14, 9]":{"[:then, 1, 11, 8, 11, 41]":2,"[:else, 2, 13, 8, 13, 73]":4},"[:if, 3, 20, 4, 24, 7]":{"[:then, 4, 21, 6, 21, 75]":2,"[:else, 5, 23, 6, 23, 71]":2},"[:if, 6, 34, 4, 34, 80]":{"[:then, 7, 34, 4, 34, 10]":6,"[:else, 8, 34, 4, 34, 80]":4}}},"covered_strength":7.2631578947368425,"covered_lines":19,"lines_of_code":19},{"filename":"/home/user/git/libregig/app/controllers/users/registration_controller.rb","covered_percent":100.0,"coverage":{"lines":[9,9,null,null,null,null,9,null,null,9,2,null,null,9,8,8,null,null,8,6,6,2,null,null,null,6,2,2,null,null,2,2,null,null,null,9,6,6,null,null,6,null,4,2,2,2,2,null,2,2,null,null,2,2,null,null,null,9,null,9,4,4,null,null],"branches":{"[:unless, 0, 11, 4, 11, 76]":{"[:else, 1, 11, 4, 11, 76]":0,"[:then, 2, 11, 4, 11, 52]":2},"[:if, 3, 21, 6, 24, 9]":{"[:then, 4, 22, 8, 23, 53]":2,"[:else, 5, 21, 6, 24, 9]":4},"[:\"\u0026.\", 6, 26, 9, 26, 48]":{"[:then, 7, 26, 9, 26, 48]":2,"[:else, 8, 26, 9, 26, 48]":4},"[:if, 9, 26, 6, 29, 9]":{"[:then, 10, 27, 8, 28, 33]":2,"[:else, 11, 26, 6, 29, 9]":4},"[:\"\u0026.\", 12, 43, 9, 43, 49]":{"[:then, 13, 43, 9, 43, 49]":4,"[:else, 14, 43, 9, 43, 49]":0},"[:if, 15, 43, 6, 51, 9]":{"[:then, 16, 44, 8, 47, 30]":2,"[:else, 17, 49, 8, 50, 33]":2},"[:if, 18, 62, 4, 62, 48]":{"[:then, 19, 62, 4, 62, 28]":2,"[:else, 20, 62, 4, 62, 48]":2}}},"covered_strength":5.0588235294117645,"covered_lines":34,"lines_of_code":34},{"filename":"/home/user/git/libregig/app/controllers/users_controller.rb","covered_percent":100.0,"coverage":{"lines":[12,12,null,null,null,null,12,null,null,null,null,12,null,null,null,null,12,2,null,null,12,8,null,8,2,2,null,null,6,4,4,null,2,null,null,null,12,null,null,12,8,8,8,null,null,8,4,4,null,4,4,null,null,null,null,12,null,12,8,null,null,null,null,null,null,null,null,null,null,12,8,null,null,null,null,null,null,null,null,12,12,12,null,null,12,12,null,null,12,12,null,null],"branches":{"[:if, 0, 24, 4, 27, 7]":{"[:then, 1, 25, 6, 26, 55]":2,"[:else, 2, 24, 4, 27, 7]":6},"[:if, 3, 29, 4, 34, 7]":{"[:then, 4, 30, 6, 31, 81]":4,"[:else, 5, 33, 6, 33, 48]":2},"[:if, 6, 41, 4, 44, 7]":{"[:then, 7, 42, 6, 43, 50]":8,"[:else, 8, 41, 4, 44, 7]":0},"[:if, 9, 46, 4, 53, 7]":{"[:then, 10, 47, 6, 48, 29]":4,"[:else, 11, 50, 6, 52, 26]":4},"[:unless, 12, 82, 4, 82, 39]":{"[:else, 13, 82, 4, 82, 39]":12,"[:then, 14, 82, 4, 82, 26]":0},"[:unless, 15, 90, 4, 90, 53]":{"[:else, 16, 90, 4, 90, 53]":10,"[:then, 17, 90, 4, 90, 28]":2}}},"covered_strength":8.594594594594595,"covered_lines":37,"lines_of_code":37},{"filename":"/home/user/git/libregig/app/helpers/application_helper.rb","covered_percent":100.0,"coverage":{"lines":[1,1,288,null,null,1,808,268,null,null,null,1,null,null,null,null,null,null,442,442,442,null,442,18,18,null,424,null,null,442,442,null,442,null,null,null,442,null,442,null,null,1,274,274,12,null,null,274,274,274,null,null,null,1,null,1,18,6,2,10,null,null,null,1,274,null,null,1,274,274,274,274,null,null,null,null],"branches":{"[:\"\u0026.\", 0, 19, 50, 19, 70]":{"[:then, 1, 19, 50, 19, 70]":64,"[:else, 2, 19, 50, 19, 70]":378},"[:if, 3, 23, 4, 28, 7]":{"[:then, 4, 24, 6, 25, 61]":18,"[:else, 5, 27, 6, 27, 49]":424},"[:if, 6, 24, 27, 24, 77]":{"[:then, 7, 24, 63, 24, 69]":6,"[:else, 8, 24, 72, 24, 77]":12},"[:if, 9, 31, 4, 31, 72]":{"[:then, 10, 31, 4, 31, 45]":110,"[:else, 11, 31, 4, 31, 72]":332},"[:if, 12, 44, 6, 46, 9]":{"[:then, 13, 45, 8, 45, 29]":12,"[:else, 14, 44, 6, 46, 9]":262},"[:case, 15, 57, 4, 61, 7]":{"[:when, 16, 58, 20, 58, 39]":6,"[:when, 17, 59, 21, 59, 40]":2,"[:else, 18, 60, 9, 60, 11]":10}}},"covered_strength":220.48717948717947,"covered_lines":39,"lines_of_code":39},{"filename":"/home/user/git/libregig/app/helpers/bands_helper.rb","covered_percent":100.0,"coverage":{"lines":[1,null],"branches":{}},"covered_strength":1.0,"covered_lines":1,"lines_of_code":1},{"filename":"/home/user/git/libregig/app/helpers/events_helper.rb","covered_percent":61.29032258064516,"coverage":{"lines":[1,1,280,2,260,18,null,null,null,1,268,2,null,null,1,280,280,10,null,null,1,280,280,280,null,null,1,2,null,0,0,null,0,0,null,0,null,0,0,0,0,null,0,0,null,0,null,null,null],"branches":{"[:case, 0, 3, 4, 7, 7]":{"[:when, 1, 4, 21, 4, 32]":2,"[:when, 2, 5, 28, 5, 41]":260,"[:else, 3, 6, 9, 6, 15]":18},"[:unless, 4, 11, 4, 11, 67]":{"[:else, 5, 11, 4, 11, 67]":2,"[:then, 6, 11, 4, 11, 17]":266},"[:unless, 7, 17, 4, 17, 68]":{"[:else, 8, 17, 4, 17, 68]":10,"[:then, 9, 17, 4, 17, 17]":270},"[:if, 10, 23, 10, 23, 52]":{"[:then, 11, 23, 40, 23, 45]":6,"[:else, 12, 23, 48, 23, 52]":274},"[:if, 13, 28, 4, 28, 30]":{"[:then, 14, 28, 4, 28, 14]":2,"[:else, 15, 28, 4, 28, 30]":0},"[:if, 16, 39, 4, 39, 61]":{"[:then, 17, 39, 4, 39, 49]":0,"[:else, 18, 39, 4, 39, 61]":0},"[:unless, 19, 39, 27, 39, 47]":{"[:else, 20, 39, 27, 39, 47]":0,"[:then, 21, 39, 27, 39, 30]":0},"[:if, 22, 40, 4, 40, 65]":{"[:then, 23, 40, 4, 40, 52]":0,"[:else, 24, 40, 4, 40, 65]":0},"[:unless, 25, 40, 29, 40, 50]":{"[:else, 26, 40, 29, 40, 50]":0,"[:then, 27, 40, 29, 40, 32]":0},"[:if, 28, 41, 4, 41, 73]":{"[:then, 29, 41, 4, 41, 58]":0,"[:else, 30, 41, 4, 41, 73]":0},"[:unless, 31, 41, 33, 41, 56]":{"[:else, 32, 41, 33, 41, 56]":0,"[:then, 33, 41, 33, 41, 36]":0},"[:case, 34, 43, 4, 47, 7]":{"[:when, 35, 44, 16, 44, 27]":0,"[:else, 36, 46, 6, 46, 53]":0}}},"covered_strength":72.51612903225806,"covered_lines":19,"lines_of_code":31},{"filename":"/home/user/git/libregig/app/helpers/members_helper.rb","covered_percent":100.0,"coverage":{"lines":[1,null],"branches":{}},"covered_strength":1.0,"covered_lines":1,"lines_of_code":1},{"filename":"/home/user/git/libregig/app/helpers/permissions_helper.rb","covered_percent":92.0,"coverage":{"lines":[1,1,8,null,null,1,132,132,396,null,null,null,1,38,16,12,10,0,null,null,null,1,38,36,2,0,null,null,null,null,null,1,null,1,396,396,396,396,152,null,null,null],"branches":{"[:case, 0, 14, 4, 19, 7]":{"[:when, 1, 15, 21, 15, 64]":16,"[:when, 2, 16, 19, 16, 58]":12,"[:when, 3, 17, 20, 17, 61]":10,"[:else, 4, 18, 9, 18, 49]":0},"[:if, 5, 23, 4, 29, 7]":{"[:then, 6, 24, 13, 24, 48]":36,"[:else, 7, 25, 4, 28, 16]":2},"[:if, 8, 25, 4, 28, 16]":{"[:then, 9, 26, 13, 26, 19]":0,"[:else, 10, 25, 4, 28, 16]":2}}},"covered_strength":102.52,"covered_lines":23,"lines_of_code":25},{"filename":"/home/user/git/libregig/app/helpers/sessions_helper.rb","covered_percent":100.0,"coverage":{"lines":[1,null],"branches":{}},"covered_strength":1.0,"covered_lines":1,"lines_of_code":1},{"filename":"/home/user/git/libregig/app/helpers/users/registration_helper.rb","covered_percent":100.0,"coverage":{"lines":[1,null],"branches":{}},"covered_strength":1.0,"covered_lines":1,"lines_of_code":1},{"filename":"/home/user/git/libregig/app/jobs/application_job.rb","covered_percent":100.0,"coverage":{"lines":[2,null,null,null,null,null,null],"branches":{}},"covered_strength":2.0,"covered_lines":1,"lines_of_code":1},{"filename":"/home/user/git/libregig/app/jobs/send_mail_job.rb","covered_percent":66.66666666666667,"coverage":{"lines":[2,2,2,null,2,0,0,null,null],"branches":{}},"covered_strength":1.3333333333333333,"covered_lines":4,"lines_of_code":6},{"filename":"/home/user/git/libregig/app/lib/form_builders/nice_form_builder.rb","covered_percent":100.0,"coverage":{"lines":[14,14,14,null,null,null,null,null,null,null,null,null,null,14,14,14,14,14,14,14,null,14,252,200,100,null,100,null,null,null,null,14,48,48,null,48,null,null,14,22,22,null,22,22,null,null,null,null,null,null,null,22,null,null,14,null,null,null,null,null,null,null,null,6,null,6,null,null,null,null,null,6,null,6,null,6,null,null,null,null,null,null,null,null,null,6,null,null,null,null,null,null,14,12,12,null,12,12,null,null,null,null,null,null,null,null,null,12,12,null,12,null,null,null,null,null,null,14,12,12,null,12,12,null,null,null,null,null,null,null,null,null,12,12,null,12,null,null,null,null,null,null,14,null,14,100,100,100,null,null,100,null,null,null,100,100,null,100,null,null,14,152,152,null,152,null,null,14,null,160,null,null,null,160,null,160,160,null,160,null,null,null,null,14,152,null,152,null,8,null,8,null,null,null,null,null,null,14,200,152,null,null,14,null,200,null,null,null,null,null,14,null,14,310,null,null,14,404,null,404,null,null,null],"branches":{"[:if, 0, 24, 8, 28, 11]":{"[:then, 1, 25, 10, 25, 32]":100,"[:else, 2, 27, 10, 27, 56]":100},"[:if, 3, 109, 6, 109, 77]":{"[:then, 4, 109, 6, 109, 48]":12,"[:else, 5, 109, 6, 109, 77]":0},"[:if, 6, 134, 6, 134, 77]":{"[:then, 7, 134, 6, 134, 48]":12,"[:else, 8, 134, 6, 134, 77]":0},"[:if, 9, 147, 14, 147, 79]":{"[:then, 10, 147, 45, 147, 60]":0,"[:else, 11, 147, 63, 147, 79]":100},"[:\"\u0026.\", 12, 152, 15, 152, 51]":{"[:then, 13, 152, 15, 152, 51]":100,"[:else, 14, 152, 15, 152, 51]":0},"[:if, 15, 170, 8, 172, 19]":{"[:then, 16, 171, 10, 171, 49]":38,"[:else, 17, 172, 10, 172, 19]":122},"[:if, 18, 177, 6, 177, 62]":{"[:then, 19, 177, 6, 177, 34]":0,"[:else, 20, 177, 6, 177, 62]":160},"[:if, 21, 187, 6, 187, 29]":{"[:then, 22, 187, 6, 187, 12]":144,"[:else, 23, 187, 6, 187, 29]":8},"[:unless, 24, 199, 6, 199, 36]":{"[:else, 25, 199, 6, 199, 36]":152,"[:then, 26, 199, 6, 199, 15]":48},"[:if, 27, 200, 6, 200, 55]":{"[:then, 28, 200, 6, 200, 17]":8,"[:else, 29, 200, 6, 200, 55]":144},"[:unless, 30, 218, 6, 218, 62]":{"[:else, 31, 218, 6, 218, 62]":404,"[:then, 32, 218, 6, 218, 12]":0}}},"covered_strength":65.3012048192771,"covered_lines":83,"lines_of_code":83},{"filename":"/home/user/git/libregig/app/mailers/application_mailer.rb","covered_percent":100.0,"coverage":{"lines":[10,10,null],"branches":{}},"covered_strength":10.0,"covered_lines":2,"lines_of_code":2},{"filename":"/home/user/git/libregig/app/mailers/test_mailer.rb","covered_percent":0.0,"coverage":{"lines":[0,0,0,null,0,0,0,0,0,0,0],"branches":{}},"covered_strength":0.0,"covered_lines":0,"lines_of_code":10},{"filename":"/home/user/git/libregig/app/mailers/user_mailer.rb","covered_percent":87.5,"coverage":{"lines":[null,10,10,null,10,2,2,null,2,null,null,10,2,null,2,null,null,null,null,null,null,null,null,null,null,2,2,null,0,0,null,null,2,null,null,10,4,null,null,null,null,null],"branches":{"[:if, 0, 26, 4, 31, 7]":{"[:then, 1, 27, 6, 27, 45]":2,"[:else, 2, 29, 6, 30, 64]":0}}},"covered_strength":4.375,"covered_lines":14,"lines_of_code":16},{"filename":"/home/user/git/libregig/app/models/application_record.rb","covered_percent":100.0,"coverage":{"lines":[1,1,null],"branches":{}},"covered_strength":1.0,"covered_lines":2,"lines_of_code":2},{"filename":"/home/user/git/libregig/app/models/band.rb","covered_percent":100.0,"coverage":{"lines":[1,1,1,null,1,1,1,null,1,1,null,1,1,null,1,null,1,258,null,null,null,null,null,1,134,null,null,1,2,null,null,1,2,2,null,null],"branches":{"[:\"\u0026.\", 0, 25, 4, 25, 48]":{"[:then, 1, 25, 4, 25, 48]":134,"[:else, 2, 25, 4, 25, 48]":0}}},"covered_strength":20.65,"covered_lines":20,"lines_of_code":20},{"filename":"/home/user/git/libregig/app/models/band_member.rb","covered_percent":100.0,"coverage":{"lines":[17,17,17,null],"branches":{}},"covered_strength":17.0,"covered_lines":3,"lines_of_code":3},{"filename":"/home/user/git/libregig/app/models/bands_audit.rb","covered_percent":100.0,"coverage":{"lines":[4,4,null,4,null],"branches":{}},"covered_strength":4.0,"covered_lines":3,"lines_of_code":3},{"filename":"/home/user/git/libregig/app/models/concerns/auditable.rb","covered_percent":100.0,"coverage":{"lines":[1,1,null,1,3,null,null,1,32,48,null,null,null,null,null,null,null,null,1,null,1,32,null,null,1,48,null,null,1,48,null,null,1,1,3,null,null,1,32,null,null,null],"branches":{}},"covered_strength":13.526315789473685,"covered_lines":19,"lines_of_code":19},{"filename":"/home/user/git/libregig/app/models/confirmation_token.rb","covered_percent":100.0,"coverage":{"lines":[9,9,null,9,null,9,null,17,null,9,null,9,10,null,null],"branches":{}},"covered_strength":10.125,"covered_lines":8,"lines_of_code":8},{"filename":"/home/user/git/libregig/app/models/current.rb","covered_percent":100.0,"coverage":{"lines":[1,1,1,null,2573,null,1,778,778,null,null,1,5384,null,null,1,766,766,null,null,1,2,null,null,1,360,null,null,1,null,1,1544,null,null],"branches":{"[:\"\u0026.\", 0, 32, 16, 32, 32]":{"[:then, 1, 32, 16, 32, 32]":1000,"[:else, 2, 32, 16, 32, 32]":544},"[:\"\u0026.\", 3, 32, 36, 32, 60]":{"[:then, 4, 32, 36, 32, 60]":0,"[:else, 5, 32, 36, 32, 60]":544}}},"covered_strength":682.1578947368421,"covered_lines":19,"lines_of_code":19},{"filename":"/home/user/git/libregig/app/models/event.rb","covered_percent":96.875,"coverage":{"lines":[1,1,null,1,1,1,1,1,null,1,null,5,null,null,null,null,263,null,null,null,null,1,462,null,null,null,null,null,1,1,null,1,134,null,null,1,2,null,null,1,2,null,null,1,2,2,null,null,null,1,null,1,350,346,346,0,null,null,null,null,1,350,2,null,null,null],"branches":{"[:\"\u0026.\", 0, 33, 4, 33, 49]":{"[:then, 1, 33, 4, 33, 49]":134,"[:else, 2, 33, 4, 33, 49]":0},"[:if, 3, 45, 4, 47, 7]":{"[:then, 4, 46, 6, 46, 56]":2,"[:else, 5, 45, 4, 47, 7]":0},"[:if, 6, 53, 4, 58, 7]":{"[:then, 7, 54, 6, 57, 9]":346,"[:else, 8, 53, 4, 58, 7]":4},"[:if, 9, 55, 6, 57, 9]":{"[:then, 10, 56, 8, 56, 29]":0,"[:else, 11, 55, 6, 57, 9]":346},"[:if, 12, 62, 4, 64, 7]":{"[:then, 13, 63, 6, 63, 51]":2,"[:else, 14, 62, 4, 64, 7]":348}}},"covered_strength":71.375,"covered_lines":31,"lines_of_code":32},{"filename":"/home/user/git/libregig/app/models/event_band.rb","covered_percent":100.0,"coverage":{"lines":[1,1,1,null],"branches":{}},"covered_strength":1.0,"covered_lines":3,"lines_of_code":3},{"filename":"/home/user/git/libregig/app/models/events_audit.rb","covered_percent":100.0,"coverage":{"lines":[5,5,5,null],"branches":{}},"covered_strength":5.0,"covered_lines":3,"lines_of_code":3},{"filename":"/home/user/git/libregig/app/models/member.rb","covered_percent":66.66666666666667,"coverage":{"lines":[1,1,1,null,1,1,null,357,null,1,null,1,1,null,1,null,1,184,null,null,null,null,null,1,0,null,null,null,null,null,null,1,360,null,null,1,0,null,null,0,null,null,null,null,null,null,0,null,0,0,0,0,0,null,null,null,null,1,4,null,null],"branches":{"[:\"\u0026.\", 0, 25, 4, 29, 17]":{"[:then, 1, 25, 4, 29, 17]":0,"[:else, 2, 25, 4, 29, 17]":0},"[:if, 3, 37, 4, 37, 34]":{"[:then, 4, 37, 4, 37, 10]":0,"[:else, 5, 37, 4, 37, 34]":0},"[:if, 6, 47, 4, 47, 32]":{"[:then, 7, 47, 4, 47, 10]":0,"[:else, 8, 47, 4, 47, 32]":0},"[:unless, 9, 53, 8, 53, 86]":{"[:else, 10, 53, 8, 53, 86]":0,"[:then, 11, 53, 8, 53, 43]":0}}},"covered_strength":34.03703703703704,"covered_lines":18,"lines_of_code":27},{"filename":"/home/user/git/libregig/app/models/member_skill.rb","covered_percent":100.0,"coverage":{"lines":[17,17,17,null,17,null],"branches":{}},"covered_strength":17.0,"covered_lines":4,"lines_of_code":4},{"filename":"/home/user/git/libregig/app/models/members_audit.rb","covered_percent":100.0,"coverage":{"lines":[4,4,4,null],"branches":{}},"covered_strength":4.0,"covered_lines":3,"lines_of_code":3},{"filename":"/home/user/git/libregig/app/models/permission.rb","covered_percent":89.74358974358974,"coverage":{"lines":[17,17,null,17,17,17,null,17,17,17,null,17,0,0,0,null,null,null,null,null,null,17,17,17,null,17,null,17,17,17,17,null,17,17,null,17,null,null,null,null,null,null,17,null,17,910,null,124,124,null,124,6,null,null,null,17,null,910,0,null,null,null,17,910,2,null,null,null,17,910,2,null,null,null],"branches":{"[:if, 0, 46, 4, 46, 38]":{"[:then, 1, 46, 4, 46, 15]":786,"[:else, 2, 46, 4, 46, 38]":124},"[:unless, 3, 51, 4, 53, 7]":{"[:else, 4, 51, 4, 53, 7]":118,"[:then, 5, 52, 6, 52, 101]":6},"[:unless, 6, 58, 4, 60, 7]":{"[:else, 7, 58, 4, 60, 7]":910,"[:then, 8, 59, 6, 59, 51]":0},"[:unless, 9, 64, 4, 66, 7]":{"[:else, 10, 64, 4, 66, 7]":908,"[:then, 11, 65, 6, 65, 57]":2},"[:\"\u0026.\", 12, 70, 11, 70, 27]":{"[:then, 13, 70, 11, 70, 27]":910,"[:else, 14, 70, 11, 70, 27]":0},"[:\"\u0026.\", 15, 70, 31, 70, 44]":{"[:then, 16, 70, 31, 70, 44]":224,"[:else, 17, 70, 31, 70, 44]":0},"[:unless, 18, 70, 4, 72, 7]":{"[:else, 19, 70, 4, 72, 7]":908,"[:then, 20, 71, 6, 71, 56]":2}}},"covered_strength":114.02564102564102,"covered_lines":35,"lines_of_code":39},{"filename":"/home/user/git/libregig/app/models/skill.rb","covered_percent":100.0,"coverage":{"lines":[1,1,1,null,1,null],"branches":{}},"covered_strength":1.0,"covered_lines":4,"lines_of_code":4},{"filename":"/home/user/git/libregig/app/models/user.rb","covered_percent":91.89189189189189,"coverage":{"lines":[1,1,null,1,1,null,null,null,1,182,null,null,1,258,null,null,1,462,null,null,1,null,931,1,null,1,null,null,null,1,null,null,null,null,1,null,null,null,null,null,1,null,null,null,1,null,151,null,null,null,1,514,null,null,1,379,null,null,1,2,null,2,null,null,null,null,1,null,1,1962,null,null,1,0,null,null,1,0,null,null,1,0,null,null,1,978,null,null],"branches":{"[:\"\u0026.\", 0, 23, 16, 23, 32]":{"[:then, 1, 23, 16, 23, 32]":924,"[:else, 2, 23, 16, 23, 32]":6},"[:if, 3, 60, 4, 60, 49]":{"[:then, 4, 60, 4, 60, 23]":0,"[:else, 5, 60, 4, 60, 49]":2},"[:if, 6, 86, 4, 86, 50]":{"[:then, 7, 86, 4, 86, 30]":16,"[:else, 8, 86, 4, 86, 50]":962}}},"covered_strength":157.94594594594594,"covered_lines":34,"lines_of_code":37},{"filename":"/home/user/git/libregig/app/models/user_mail.rb","covered_percent":100.0,"coverage":{"lines":[1,1,null,1,null,1,1,1,1,null,1,8,null,null,1,8,null,null,1,6,null,4,null,null,4,2,2,null,2,2,2,null,null,null,1,null,1,16,null,null,null,null,null,null,null],"branches":{"[:unless, 0, 20, 4, 20, 26]":{"[:else, 1, 20, 4, 20, 26]":4,"[:then, 2, 20, 4, 20, 10]":2},"[:if, 3, 29, 6, 29, 39]":{"[:then, 4, 29, 6, 29, 13]":0,"[:else, 5, 29, 6, 29, 39]":2}}},"covered_strength":2.9565217391304346,"covered_lines":23,"lines_of_code":23},{"filename":"/home/user/git/libregig/app/queries/band_permission_query.rb","covered_percent":100.0,"coverage":{"lines":[17,17,17,258,null,null,null,null,null,null,null,null,null,null,null,null,null,null,null,null,null,null,null,null,null,null,null,null,null,null,null,17,258,null,null,null,null,null,null,null,null,null,null,null,null,null,null,null,null,null,null,null,null,17,null,17,258,null,null,null,null,null,null,17,258,null,null,null,null,null,null,null,null,null,null,null,17,258,null,null,null,null,null,null,null,null,null,null,null,17,258,null,null,null,null,null,null,null,null,null,null,null,null,null,null,null,null,null,null,17,258,null,null,null,null,null,null,null,null,null,null,null,null,null,null,null,null,null,null,null,null,null,null,null],"branches":{}},"covered_strength":116.23529411764706,"covered_lines":17,"lines_of_code":17},{"filename":"/home/user/git/libregig/app/queries/event_permission_query.rb","covered_percent":100.0,"coverage":{"lines":[17,17,17,462,null,null,null,null,null,null,null,null,null,null,null,null,null,null,null,null,17,462,null,null,null,null,null,null,null,null,null,null,null,null,null,null,null,null,null,null,null,null,17,null,17,462,null,null,null,null,null,null,17,462,null,null,null,null,null,null,null,null,null,null,null,17,462,null,null,null,null,null,null,null,null,null,null,null,null,null,null,null,null,null,null],"branches":{}},"covered_strength":188.15384615384616,"covered_lines":13,"lines_of_code":13},{"filename":"/home/user/git/libregig/app/queries/member_permission_query.rb","covered_percent":100.0,"coverage":{"lines":[17,17,17,184,null,null,null,null,null,null,null,null,null,null,null,null,null,null,null,null,null,null,null,null,null,null,null,null,null,null,null,null,null,null,null,17,184,null,null,null,null,null,null,null,null,null,null,null,null,null,null,null,null,null,null,null,null,17,184,null,null,null,null,null,null,17,184,null,null,null,null,null,null,null,null,null,null,17,184,null,null,null,null,null,null,null,null,null,null,null,null,null,null,17,194,null,null,null,null,null,null,null,null,null,null,null,null,null,null,null,null,17,184,null,null,null,null,null,null,null,null,null,null,null,null,null,null,null,null,null,null,null,null,null,null,17,184,null,null,null,null,null,null,null,null,null,null,null,null,null,null,null,null,null,null,null,null],"branches":{}},"covered_strength":91.77777777777777,"covered_lines":18,"lines_of_code":18}],"metrics":{"covered_percent":89.86960882647944,"covered_strength":71.02407221664996,"covered_lines":896,"total_lines":997}}
